README.md
setup.cfg
setup.py
SecondaryValue/SecondaryValue.py
SecondaryValue/__init__.py
SecondaryValue/test_secondaryvalue.py
SecondaryValue.egg-info/PKG-INFO
SecondaryValue.egg-info/PKG-INFO.sync-conflict-20190518-100324-VRZ7D3U
SecondaryValue.egg-info/SOURCES.txt
SecondaryValue.egg-info/dependency_links.txt
SecondaryValue.egg-info/requires.txt
SecondaryValue.egg-info/top_level.txt
SecondaryValue.egg-info/zip-safe