Metadata-Version: 2.1
Name: SecondaryValue
Version: 0.2.0
Summary: A helper to calculate the gaussian error propagation.
Home-page: https://github.com/vale981/SecondaryValue
Author: Valentin Boettcher
Author-email: hiro@protagon.space
License: GPLv3.0
Keywords: gaussian error propagation
Platform: UNKNOWN
